autoreviewufzvs/__init__.py
autoreviewufzvs/__main__.py
autoreviewufzvs/concatenate_xls.py
autoreviewufzvs/ordering.py
autoreviewufzvs/script_highlight.py
autoreviewufzvs/script_highlight_excel.py
autoreview_ufz_VS-1.0.2.dist-info/LICENCE
autoreview_ufz_VS-1.0.2.dist-info/METADATA
autoreview_ufz_VS-1.0.2.dist-info/WHEEL
autoreview_ufz_VS-1.0.2.dist-info/entry_points.txt
autoreview_ufz_VS-1.0.2.dist-info/top_level.txt
autoreview_ufz_VS-1.0.2.dist-info/RECORD
