Metadata-Version: 2.1
Name: autoreview-ufz-VS
Version: 1.0.2
Summary: A package for automating operations on Excel files.
Home-page: https://github.com/your_github_username/autoreviewufzvs
Author: Vianney Sicard
Author-email: vianney.sicard@ufz.de
Classifier: Programming Language :: Python :: 3.9
Classifier: License :: OSI Approved :: GNU General Public License v3 (GPLv3)
Classifier: Operating System :: OS Independent
Classifier: Development Status :: 4 - Beta
Classifier: Intended Audience :: Developers
Classifier: Intended Audience :: Science/Research
Classifier: Topic :: Software Development :: Libraries
Classifier: Topic :: Scientific/Engineering
Requires-Python: >=3.9
License-File: LICENCE
Requires-Dist: pandas <2.0.0,>=1.1.0
Requires-Dist: tqdm >=4.0.0
Requires-Dist: numpy >=1.18.0
Requires-Dist: python-docx >=1.1.2
Requires-Dist: XlsxWriter >=3.2.0
Requires-Dist: scikit-learn >=1.5.2
